ai_prishtina_text2sql_ltm-1.0.10.dist-info/licenses/LICENSE
text2sql_ltm/__init__.py
text2sql_ltm/agent.py
text2sql_ltm/cli.py
text2sql_ltm/config.py
text2sql_ltm/context.py
text2sql_ltm/exceptions.py
text2sql_ltm/factory.py
text2sql_ltm/schema.py
text2sql_ltm/session.py
text2sql_ltm/types.py
text2sql_ltm/ai_features/__init__.py
text2sql_ltm/ai_features/config.py
text2sql_ltm/ai_features/explainer.py
text2sql_ltm/ai_features/query_translator.py
text2sql_ltm/ai_features/schema_discovery.py
text2sql_ltm/ai_features/security_analyzer.py
text2sql_ltm/ai_features/sql_validator.py
text2sql_ltm/ai_features/test_generator.py
text2sql_ltm/config/__init__.py
text2sql_ltm/config/agent.py
text2sql_ltm/config/base.py
text2sql_ltm/config/memory.py
text2sql_ltm/config/monitoring.py
text2sql_ltm/config/performance.py
text2sql_ltm/config/security.py
text2sql_ltm/llm/__init__.py
text2sql_ltm/llm/anthropic_provider.py
text2sql_ltm/llm/base.py
text2sql_ltm/llm/factory.py
text2sql_ltm/llm/google_provider.py
text2sql_ltm/llm/huggingface_provider.py
text2sql_ltm/llm/local_provider.py
text2sql_ltm/llm/openai_provider.py
text2sql_ltm/memory/__init__.py
text2sql_ltm/memory/manager.py
text2sql_ltm/memory/simple_manager.py
text2sql_ltm/memory/storage.py
text2sql_ltm/rag/__init__.py
text2sql_ltm/rag/adaptive_rag.py
text2sql_ltm/rag/augmentor.py
text2sql_ltm/rag/embeddings.py
text2sql_ltm/rag/faiss_store.py
text2sql_ltm/rag/manager.py
text2sql_ltm/rag/pgvector_store.py
text2sql_ltm/rag/pinecone_store.py
text2sql_ltm/rag/qdrant_store.py
text2sql_ltm/rag/query_rag.py
text2sql_ltm/rag/redis_store.py
text2sql_ltm/rag/retriever.py
text2sql_ltm/rag/schema_rag.py
text2sql_ltm/rag/vector_store.py
text2sql_ltm/rag/weaviate_store.py
ai_prishtina_text2sql_ltm-1.0.10.dist-info/METADATA
ai_prishtina_text2sql_ltm-1.0.10.dist-info/WHEEL
ai_prishtina_text2sql_ltm-1.0.10.dist-info/top_level.txt
ai_prishtina_text2sql_ltm-1.0.10.dist-info/RECORD
