Metadata-Version: 2.4
Name: ai-prishtina-text2sql-ltm
Version: 1.0.10
Summary: Advanced Text-to-SQL library with AI features
Home-page: https://github.com/albanmaxhuni/text2sql-ltm
Author: Alban Maxhuni, PhD
Author-email: "Alban Maxhuni, PhD" <info@albanmaxhuni.com>
Maintainer-email: "Alban Maxhuni, PhD" <info@albanmaxhuni.com>
License: Commercial
Project-URL: Homepage, https://github.com/AI-Prishtina/ai-prishtina-text2sql-ltm
Project-URL: Documentation, https://github.com/AI-Prishtina/ai-prishtina-text2sql-ltm/blob/main/README.md
Project-URL: Repository, https://github.com/AI-Prishtina/ai-prishtina-text2sql-ltm
Project-URL: Bug Tracker, https://github.com/AI-Prishtina/ai-prishtina-text2sql-ltm/issues
Project-URL: Changelog, https://github.com/AI-Prishtina/ai-prishtina-text2sql-ltm/blob/main/CHANGELOG.md
Project-URL: Funding, https://coff.ee/albanmaxhuni
Keywords: text2sql,sql,natural-language-processing,nlp,ai,machine-learning,database,query-generation,rag,vector-database,llm,openai,anthropic,memory,long-term-memory,sql-validation,security-analysis,query-translation,schema-discovery,multimodal,voice-to-sql,image-to-sql,enterprise,production-ready
Platform: any
Classifier: Development Status :: 5 - Production/Stable
Classifier: Intended Audience :: Developers
Classifier: Intended Audience :: Information Technology
Classifier: Intended Audience :: Science/Research
Classifier: Topic :: Database
Classifier: Topic :: Scientific/Engineering :: Artificial Intelligence
Classifier: Topic :: Software Development :: Libraries :: Python Modules
Classifier: License :: Other/Proprietary License
Classifier: Programming Language :: Python :: 3
Classifier: Programming Language :: Python :: 3.8
Classifier: Programming Language :: Python :: 3.9
Classifier: Programming Language :: Python :: 3.10
Classifier: Programming Language :: Python :: 3.11
Classifier: Programming Language :: Python :: 3.12
Classifier: Operating System :: OS Independent
Requires-Python: >=3.8
License-File: LICENSE
Requires-Dist: pydantic>=2.0.0
Requires-Dist: pyyaml>=6.0
Requires-Dist: numpy>=1.21.0
Requires-Dist: asyncio-mqtt>=0.11.0
Requires-Dist: aiofiles>=23.0.0
Requires-Dist: typing-extensions>=4.0.0
Provides-Extra: rag
Requires-Dist: chromadb>=0.4.0; extra == "rag"
Requires-Dist: sentence-transformers>=2.2.0; extra == "rag"
Requires-Dist: faiss-cpu>=1.7.0; extra == "rag"
Provides-Extra: llm
Requires-Dist: openai>=1.0.0; extra == "llm"
Requires-Dist: anthropic>=0.3.0; extra == "llm"
Provides-Extra: memory
Requires-Dist: redis>=4.0.0; extra == "memory"
Requires-Dist: psycopg2-binary>=2.9.0; extra == "memory"
Requires-Dist: pymongo>=4.0.0; extra == "memory"
Provides-Extra: vector
Requires-Dist: pinecone-client>=2.0.0; extra == "vector"
Requires-Dist: weaviate-client>=3.0.0; extra == "vector"
Requires-Dist: qdrant-client>=1.0.0; extra == "vector"
Requires-Dist: milvus>=2.0.0; extra == "vector"
Provides-Extra: all
Requires-Dist: ai-prishtina-text2sql-ltm[llm,memory,rag,vector]; extra == "all"
Provides-Extra: dev
Requires-Dist: pytest>=7.0.0; extra == "dev"
Requires-Dist: pytest-asyncio>=0.21.0; extra == "dev"
Requires-Dist: pytest-cov>=4.0.0; extra == "dev"
Requires-Dist: black>=23.0.0; extra == "dev"
Requires-Dist: isort>=5.12.0; extra == "dev"
Requires-Dist: mypy>=1.0.0; extra == "dev"
Requires-Dist: pre-commit>=3.0.0; extra == "dev"
Dynamic: author
Dynamic: home-page
Dynamic: license-file
Dynamic: platform
Dynamic: requires-python
